prime_number_finder/__init__.py
prime_number_finder/app.py
prime_number_finder/database_handler.py
prime_number_finder/file_handler.py
prime_number_finder/prime_checker.py
prime_number_finder/resources/PYPI_README.md
prime_number_finder/resources/configs/config.yml
prime_number_finder/resources/configs/themes.yml
prime_number_finder/resources/data/prime_data.db
prime_number_finder/resources/gifs/app_showcase.gif
prime_number_finder/resources/images/prime_number_finder-128.png
prime_number_finder/resources/images/prime_number_finder-16.png
prime_number_finder/resources/images/prime_number_finder-256.png
prime_number_finder/resources/images/prime_number_finder-32.png
prime_number_finder/resources/images/prime_number_finder-512.png
prime_number_finder/resources/images/prime_number_finder-64.png
prime_number_finder-1.8.0.dist-info/METADATA
prime_number_finder-1.8.0.dist-info/WHEEL
prime_number_finder-1.8.0.dist-info/entry_points.txt
prime_number_finder-1.8.0.dist-info/licenses/LICENSE
prime_number_finder-1.8.0.dist-info/RECORD
