Metadata-Version: 2.4
Name: prime_number_finder
Version: 1.8.0
Summary: Python program for finding/checking Prime Numbers.
Project-URL: repository, https://codeberg.org/melvinquick/prime_number_finder
Project-URL: issues, https://codeberg.org/melvinquick/prime_number_finder/issues
Author-email: Melvin Quick <melvinquick@proton.me>
License-Expression: MIT
License-File: LICENSE
Requires-Python: >=3.12
Requires-Dist: pyside6>=6.8.2.1
Requires-Dist: pyyaml>=6.0.2
